LICENSE
MANIFEST.in
setup.cfg
setup.py
neowebdriver/__init__.py
neowebdriver.egg-info/PKG-INFO
neowebdriver.egg-info/SOURCES.txt
neowebdriver.egg-info/dependency_links.txt
neowebdriver.egg-info/top_level.txt